newlib/__init__.py
newlib/analysis/__init__.py
newlib/analysis/quality.py
newlib/analysis/similarity.py
newlib/analysis/stats.py
newlib/cli/main.py
newlib/core/image.py
newlib/core/interop.py
newlib/core/io.py
newlib/core/pipeline.py
newlib/transforms/augmentation.py
newlib/transforms/color.py
newlib/transforms/filtering.py
newlib/transforms/geometric.py
newlib/utils/data.py
newlib/utils/debug.py
newlib/utils/ml.py
newlib/vision/contours.py
newlib/vision/edges.py
newlib/vision/features.py
imgforge-0.1.1.dist-info/METADATA
imgforge-0.1.1.dist-info/WHEEL
imgforge-0.1.1.dist-info/entry_points.txt
imgforge-0.1.1.dist-info/top_level.txt
imgforge-0.1.1.dist-info/RECORD
