Metadata-Version: 2.4
Name: imgforge
Version: 0.1.1
Summary: A high-performance, modular Python image processing library.
Author-email: Viswa V R <viswavr54@gmail.com>
Classifier: Programming Language :: Python :: 3
Classifier: License :: OSI Approved :: MIT License
Classifier: Operating System :: OS Independent
Classifier: Topic :: Scientific/Engineering :: Image Processing
Requires-Python: >=3.9
Requires-Dist: numpy>=1.21.0
Requires-Dist: opencv-python-headless>=4.5.5
Requires-Dist: pillow>=9.0.0
Requires-Dist: pydantic>=2.0.0
Requires-Dist: typer>=0.9.0
Requires-Dist: requests>=2.25.0
Requires-Dist: rich>=13.0.0
Provides-Extra: ml
Requires-Dist: torch>=2.0.0; extra == "ml"
Requires-Dist: tensorflow>=2.10.0; (platform_system != "Darwin" or platform_machine != "arm64") and extra == "ml"
Provides-Extra: dev
Requires-Dist: pytest>=7.0.0; extra == "dev"
Requires-Dist: black>=23.0.0; extra == "dev"
Requires-Dist: mypy>=1.0.0; extra == "dev"
Requires-Dist: matplotlib>=3.5.0; extra == "dev"
